LICENSE.txt
MANIFEST.in
README.rst
requirements.txt
setup.py
bocho/__init__.py
bocho/cmd.py
bocho/config.py
bocho/transforms.py
bocho/utils.py
deba_bocho.egg-info/PKG-INFO
deba_bocho.egg-info/SOURCES.txt
deba_bocho.egg-info/dependency_links.txt
deba_bocho.egg-info/entry_points.txt
deba_bocho.egg-info/requires.txt
deba_bocho.egg-info/top_level.txt