Metadata-Version: 1.1
Name: deba-bocho
Version: 0.5.2
Summary: Slice up PDFs like a pro.
Home-page: https://github.com/jimr/deba-bocho
Author: James Rutherford
Author-email: jim@jimr.org
License: MIT
Platform: UNKNOWN
Classifier: Development Status :: 4 - Beta
Classifier: Environment :: Console
Classifier: License :: OSI Approved :: MIT License
Classifier: Operating System :: POSIX :: Linux
Classifier: Programming Language :: Python
Classifier: Programming Language :: Python :: Implementation :: PyPy
Classifier: Programming Language :: Python :: 2
Classifier: Programming Language :: Python :: 2.7
Classifier: Programming Language :: Python :: 3
Classifier: Topic :: Multimedia :: Graphics :: Graphics Conversion
Provides: bocho
